{
  "_meta": {
    "cash": 8718.713609828133,
    "peak_equity": 10390.48381505795
  },
  "BTCUSDT": {
    "in_position": false,
    "entry": null,
    "high": null,
    "qty": 0.0,
    "last_trade": 1783308677.787798
  },
  "ETHUSDT": {
    "in_position": false,
    "entry": null,
    "high": null,
    "qty": 0.0,
    "last_trade": 1783296104.2640064
  },
  "SOLUSDT": {
    "in_position": false,
    "entry": null,
    "high": null,
    "qty": 0.0,
    "last_trade": 1783306882.0702586
  },
  "BNBUSDT": {
    "in_position": false,
    "entry": null,
    "high": null,
    "qty": 0.0,
    "last_trade": 1783304157.526497
  },
  "XRPUSDT": {
    "in_position": false,
    "entry": null,
    "high": null,
    "qty": 0.0,
    "last_trade": 1783314964.2549114
  },
  "ADAUSDT": {
    "in_position": false,
    "entry": null,
    "high": null,
    "qty": 0.0,
    "last_trade": 1783306882.0702696
  },
  "AVAXUSDT": {
    "in_position": false,
    "entry": null,
    "high": null,
    "qty": 0.0,
    "last_trade": 1783315883.0835483
  },
  "LINKUSDT": {
    "in_position": false,
    "entry": null,
    "high": null,
    "qty": 0.0,
    "last_trade": 1783296143.0174327
  },
  "LTCUSDT": {
    "in_position": false,
    "entry": null,
    "high": null,
    "qty": 0.0,
    "last_trade": 1783304170.1799595
  },
  "DOGEUSDT": {
    "in_position": false,
    "entry": null,
    "high": null,
    "qty": 0.0,
    "last_trade": 1783297904.1192565
  }
}